risknet/__init__.py
risknet/main.py
risknet/config/__init__.py
risknet/config/conf.yaml
risknet/config/handlers.py
risknet/data/__init__.py
risknet/jobs/__init__.py
risknet/jobs/cloud_etl.py
risknet/proc/__init__.py
risknet/proc/encoder.py
risknet/proc/label_prep.py
risknet/proc/reducer.py
risknet/run/__init__.py
risknet/run/main.py
risknet/run/model.py
risknet/run/pipeline.py
risknet/sys/__init__.py
risknet/sys/log.py
risknet/sys/managers.py
risknet/sys/system.py
risknet-1.0.17.dist-info/LICENSE
risknet-1.0.17.dist-info/METADATA
risknet-1.0.17.dist-info/WHEEL
risknet-1.0.17.dist-info/top_level.txt
risknet-1.0.17.dist-info/RECORD
