Metadata-Version: 2.1
Name: risknet
Version: 1.0.17
Summary: A pip-installable pipeline which loads 2009 FM data into an XGBoost model instance
Home-page: https://github.com/prod-lab/risknet
Author: Zaki Ahmed, Rod Albuyeh, Terin Ambat, Emily Chin, Zhen Fang, Riya Mhatre, Zafeer Syed
Author-email: zahmed@ucsd.edu, albuyeh@gmail.com, tambat@ucsd.edu, e1chin@ucsd.edu, zhfang@ucsd.edu, rmhatre@ucsd.edu, zsyed@ucsd.edu
Project-URL: Bug Tracker, https://github.com/prod-lab/risknet/issues
Classifier: Intended Audience :: Developers
Classifier: Programming Language :: Python
Classifier: Programming Language :: Python :: 3.6
Classifier: Programming Language :: Python :: 3.7
Classifier: Programming Language :: Python :: 3.8
Classifier: Programming Language :: Python :: 3.8
Classifier: License :: OSI Approved :: MIT License
Classifier: Operating System :: OS Independent
Classifier: Topic :: Software Development :: Libraries :: Python Modules
Requires-Python: >=3.10
License-File: LICENSE
Requires-Dist: numpy ==1.26.1
Requires-Dist: pandas ==2.1.2
Requires-Dist: dask[complete] ==2023.10.1
Requires-Dist: xgboost ==2.0.1
Requires-Dist: PyYAML
Requires-Dist: types-PyYAML
Requires-Dist: pyarrow
Requires-Dist: fastparquet
